artificial_terrains/__init__.py
artificial_terrains/generate_terrain.py
artificial_terrains/print_installed_packages.py
artificial_terrains/modules/__init__.py
artificial_terrains/modules/blender.py
artificial_terrains/modules/combining.py
artificial_terrains/modules/general.py
artificial_terrains/modules/generating.py
artificial_terrains/modules/generating_function.py
artificial_terrains/modules/loop.py
artificial_terrains/modules/modifiers.py
artificial_terrains/modules/module.py
artificial_terrains/modules/modules.py
artificial_terrains/modules/other.py
artificial_terrains/modules/plot.py
artificial_terrains/modules/terrain.py
artificial_terrains/runs/data_046_parameterize/02_test/test.py
artificial_terrains/runs/data_046_parameterize/02_test/test2.py
artificial_terrains/utils/Blender.py
artificial_terrains/utils/artificial_shapes.py
artificial_terrains/utils/debug.py
artificial_terrains/utils/examples.py
artificial_terrains/utils/examples2.py
artificial_terrains/utils/interpolator.py
artificial_terrains/utils/logging_utils.py
artificial_terrains/utils/noise.py
artificial_terrains/utils/obstacles.py
artificial_terrains/utils/parse_utils.py
artificial_terrains/utils/plots.py
artificial_terrains/utils/terrains.py
artificial_terrains/utils/utils.py
artificial_terrains-0.15.dist-info/licenses/LICENCE.md
artificial_terrains-0.15.dist-info/METADATA
artificial_terrains-0.15.dist-info/WHEEL
artificial_terrains-0.15.dist-info/entry_points.txt
artificial_terrains-0.15.dist-info/top_level.txt
artificial_terrains-0.15.dist-info/RECORD
