Metadata-Version: 2.4
Name: artificial-terrains
Version: 0.15
Summary: Modular, extensible terrain generation library
Author-email: Erik Wallin <erik.wallin@umu.se>
License: MIT
Project-URL: Homepage, https://github.com/erikwallin86/artificial_terrains
License-File: LICENCE.md
Requires-Dist: numpy
Requires-Dist: matplotlib
Requires-Dist: scipy
Requires-Dist: colorcet
Requires-Dist: opensimplex
Requires-Dist: PyYaml
Requires-Dist: tifffile
Dynamic: license-file
